{
    "properties": {
        "lattice_vector_a": [
            16.34974,
            0.0,
            0.0
        ],
        "lattice_vector_b": [
            0.0,
            5.08601,
            0.0
        ],
        "lattice_vector_c": [
            -6.2746397100226785,
            0.0,
            19.40219120548776
        ]
    },
    "struct_id": "DBPERY",
    "input_ref": null,
    "geometry": [
        [
            13.712011337280273,
            2.209779739379883,
            5.1369242668151855,
            "C",
            NaN,
            NaN,
            false
        ],
        [
            -3.6369106769561768,
            2.876230239868164,
            14.265267372131348,
            "C",
            NaN,
            NaN,
            false
        ],
        [
            4.537111282348633,
            2.208503246307373,
            14.266120910644531,
            "C",
            NaN,
            NaN,
            false
        ],
        [
            5.537989139556885,
            2.877506732940674,
            5.136070251464844,
            "C",
            NaN,
            NaN,
            false
        ],
        [
            10.583669662475586,
            4.752357482910156,
            14.840639114379883,
            "C",
            NaN,
            NaN,
            false
        ],
        [
            -0.5085698366165161,
            0.33365243673324585,
            4.561552047729492,
            "C",
            NaN,
            NaN,
            false
        ],
        [
            7.6673197746276855,
            4.753456115722656,
            4.561028480529785,
            "C",
            NaN,
            NaN,
            false
        ],
        [
            2.407780647277832,
            0.3325538635253906,
            14.84116268157959,
            "C",
            NaN,
            NaN,
            false
        ],
        [
            14.133536338806152,
            1.2624138593673706,
            6.138853073120117,
            "C",
            NaN,
            NaN,
            false
        ],
        [
            -4.058436393737793,
            3.823596239089966,
            13.263338088989258,
            "C",
            NaN,
            NaN,
            false
        ],
        [
            4.115711212158203,
            1.260872721672058,
            13.264307975769043,
            "C",
            NaN,
            NaN,
            false
        ],
        [
            5.9593892097473145,
            3.8251373767852783,
            6.137883186340332,
            "C",
            NaN,
            NaN,
            false
        ],
        [
            11.004573822021484,
            3.804330348968506,
            15.842063903808594,
            "C",
            NaN,
            NaN,
            false
        ],
        [
            -0.9294739365577698,
            1.281679630279541,
            3.5601274967193604,
            "C",
            NaN,
            NaN,
            false
        ],
        [
            7.246592044830322,
            3.8051085472106934,
            3.55981707572937,
            "C",
            NaN,
            NaN,
            false
        ],
        [
            2.8285083770751953,
            1.2809014320373535,
            15.842373847961426,
            "C",
            NaN,
            NaN,
            false
        ],
        [
            14.3247709274292,
            2.2144081592559814,
            3.851625919342041,
            "C",
            NaN,
            NaN,
            false
        ],
        [
            -4.2496867179870605,
            2.8716018199920654,
            15.550564765930176,
            "C",
            NaN,
            NaN,
            false
        ],
        [
            3.9244205951690674,
            2.2129383087158203,
            15.551457405090332,
            "C",
            NaN,
            NaN,
            false
        ],
        [
            6.150679588317871,
            2.8730719089508057,
            3.850733518600464,
            "C",
            NaN,
            NaN,
            false
        ],
        [
            11.197348594665527,
            4.758003234863281,
            13.555787086486816,
            "C",
            NaN,
            NaN,
            false
        ],
        [
            -1.1222479343414307,
            0.32800695300102234,
            5.846404075622559,
            "C",
            NaN,
            NaN,
            false
        ],
        [
            7.0537109375,
            4.7589592933654785,
            5.845919132232666,
            "C",
            NaN,
            NaN,
            false
        ],
        [
            3.0213894844055176,
            0.3270507752895355,
            13.556272506713867,
            "C",
            NaN,
            NaN,
            false
        ],
        [
            13.865121841430664,
            3.1197025775909424,
            2.891392230987549,
            "C",
            NaN,
            NaN,
            false
        ],
        [
            -3.7900376319885254,
            1.9663022756576538,
            16.510799407958984,
            "C",
            NaN,
            NaN,
            false
        ],
        [
            4.3843464851379395,
            3.118008852005005,
            16.5118465423584,
            "C",
            NaN,
            NaN,
            false
        ],
        [
            5.690753936767578,
            1.9680010080337524,
            2.8903443813323975,
            "C",
            NaN,
            NaN,
            false
        ],
        [
            10.739418029785156,
            0.579271137714386,
            12.596659660339355,
            "C",
            NaN,
            NaN,
            false
        ],
        [
            -0.6643176078796387,
            4.506738662719727,
            6.805531978607178,
            "C",
            NaN,
            NaN,
            false
        ],
        [
            7.511911869049072,
            0.5798356533050537,
            6.8052215576171875,
            "C",
            NaN,
            NaN,
            false
        ],
        [
            2.5631885528564453,
            4.506174564361572,
            12.596969604492188,
            "C",
            NaN,
            NaN,
            false
        ],
        [
            12.860502243041992,
            4.039878845214844,
            3.183434009552002,
            "C",
            NaN,
            NaN,
            false
        ],
        [
            -2.7854015827178955,
            1.0461312532424927,
            16.21875762939453,
            "C",
            NaN,
            NaN,
            false
        ],
        [
            5.388751029968262,
            4.0383124351501465,
            16.2196102142334,
            "C",
            NaN,
            NaN,
            false
        ],
        [
            4.686349391937256,
            1.0477027893066406,
            3.1825802326202393,
            "C",
            NaN,
            NaN,
            false
        ],
        [
            9.734418869018555,
            1.4989793300628662,
            12.888914108276367,
            "C",
            NaN,
            NaN,
            false
        ],
        [
            0.3406815826892853,
            3.5870306491851807,
            6.51327657699585,
            "C",
            NaN,
            NaN,
            false
        ],
        [
            8.51662826538086,
            1.499869465827942,
            6.51283073425293,
            "C",
            NaN,
            NaN,
            false
        ],
        [
            1.5584723949432373,
            3.5861406326293945,
            12.889360427856445,
            "C",
            NaN,
            NaN,
            false
        ],
        [
            12.281768798828125,
            4.064515590667725,
            4.439046859741211,
            "C",
            NaN,
            NaN,
            false
        ],
        [
            -2.2066686153411865,
            1.0214946269989014,
            14.963144302368164,
            "C",
            NaN,
            NaN,
            false
        ],
        [
            5.967155456542969,
            4.063375949859619,
            14.96390151977539,
            "C",
            NaN,
            NaN,
            false
        ],
        [
            4.107944965362549,
            1.0226339101791382,
            4.438290119171143,
            "C",
            NaN,
            NaN,
            false
        ],
        [
            9.15368938446045,
            1.521449327468872,
            14.14367389678955,
            "C",
            NaN,
            NaN,
            false
        ],
        [
            0.9214110374450684,
            3.564560651779175,
            5.258517742156982,
            "C",
            NaN,
            NaN,
            false
        ],
        [
            9.096678733825684,
            1.5229344367980957,
            5.257741451263428,
            "C",
            NaN,
            NaN,
            false
        ],
        [
            0.978421151638031,
            3.563075542449951,
            14.144449234008789,
            "C",
            NaN,
            NaN,
            false
        ],
        [
            12.676193237304688,
            3.1497251987457275,
            5.4332733154296875,
            "C",
            NaN,
            NaN,
            false
        ],
        [
            -2.601092576980591,
            1.9362796545028687,
            13.968917846679688,
            "C",
            NaN,
            NaN,
            false
        ],
        [
            5.57266092300415,
            3.148667335510254,
            13.969538688659668,
            "C",
            NaN,
            NaN,
            false
        ],
        [
            4.502439022064209,
            1.937342643737793,
            5.432652473449707,
            "C",
            NaN,
            NaN,
            false
        ],
        [
            9.54702377319336,
            0.6053724884986877,
            15.137124061584473,
            "C",
            NaN,
            NaN,
            false
        ],
        [
            0.5280769467353821,
            4.480637550354004,
            4.265067100524902,
            "C",
            NaN,
            NaN,
            false
        ],
        [
            8.703409194946289,
            0.6068728566169739,
            4.264194011688232,
            "C",
            NaN,
            NaN,
            false
        ],
        [
            1.371691107749939,
            4.479136943817139,
            15.137996673583984,
            "C",
            NaN,
            NaN,
            false
        ],
        [
            12.055255889892578,
            3.155564069747925,
            6.743755340576172,
            "C",
            NaN,
            NaN,
            false
        ],
        [
            -1.9801557064056396,
            1.930445909500122,
            12.658435821533203,
            "C",
            NaN,
            NaN,
            false
        ],
        [
            6.193277359008789,
            3.1548876762390137,
            12.659037590026855,
            "C",
            NaN,
            NaN,
            false
        ],
        [
            3.8818230628967285,
            1.9311224222183228,
            6.743154048919678,
            "C",
            NaN,
            NaN,
            false
        ],
        [
            8.924626350402832,
            0.6091463565826416,
            16.44696617126465,
            "C",
            NaN,
            NaN,
            false
        ],
        [
            1.1504744291305542,
            4.476863861083984,
            2.9552254676818848,
            "C",
            NaN,
            NaN,
            false
        ],
        [
            9.325605392456055,
            0.6106925010681152,
            2.954216480255127,
            "C",
            NaN,
            NaN,
            false
        ],
        [
            0.7494950294494629,
            4.475317478179932,
            16.447975158691406,
            "C",
            NaN,
            NaN,
            false
        ],
        [
            11.073017120361328,
            4.0907135009765625,
            7.133681297302246,
            "C",
            NaN,
            NaN,
            false
        ],
        [
            -0.9979164600372314,
            0.9952965378761292,
            12.268509864807129,
            "C",
            NaN,
            NaN,
            false
        ],
        [
            7.175137519836426,
            4.0903167724609375,
            12.268917083740234,
            "C",
            NaN,
            NaN,
            false
        ],
        [
            2.8999624252319336,
            0.9956932663917542,
            7.133273601531982,
            "C",
            NaN,
            NaN,
            false
        ],
        [
            7.9417619705200195,
            1.543476939201355,
            16.837356567382812,
            "C",
            NaN,
            NaN,
            false
        ],
        [
            2.133338451385498,
            3.5425331592559814,
            2.564833879470825,
            "C",
            NaN,
            NaN,
            false
        ],
        [
            10.307746887207031,
            1.545658826828003,
            2.5633788108825684,
            "C",
            NaN,
            NaN,
            false
        ],
        [
            -0.23264670372009277,
            3.540351152420044,
            16.83881187438965,
            "C",
            NaN,
            NaN,
            false
        ],
        [
            10.514995574951172,
            4.05819845199585,
            8.400023460388184,
            "C",
            NaN,
            NaN,
            false
        ],
        [
            -0.4398949444293976,
            1.0278114080429077,
            11.002167701721191,
            "C",
            NaN,
            NaN,
            false
        ],
        [
            7.732807159423828,
            4.057939052581787,
            11.002400398254395,
            "C",
            NaN,
            NaN,
            false
        ],
        [
            2.3422932624816895,
            1.0280708074569702,
            8.39979076385498,
            "C",
            NaN,
            NaN,
            false
        ],
        [
            7.382983207702637,
            1.5090904235839844,
            18.10331153869629,
            "C",
            NaN,
            NaN,
            false
        ],
        [
            2.692117214202881,
            3.5769195556640625,
            1.2988797426223755,
            "C",
            NaN,
            NaN,
            false
        ],
        [
            10.866275787353516,
            1.5114401578903198,
            1.2972886562347412,
            "C",
            NaN,
            NaN,
            false
        ],
        [
            -0.7911752462387085,
            3.5745699405670166,
            18.104902267456055,
            "C",
            NaN,
            NaN,
            false
        ],
        [
            10.89778995513916,
            3.0684609413146973,
            9.32434368133545,
            "C",
            NaN,
            NaN,
            false
        ],
        [
            -0.8226898312568665,
            2.0175490379333496,
            10.077847480773926,
            "C",
            NaN,
            NaN,
            false
        ],
        [
            7.350092887878418,
            3.0680744647979736,
            10.078235626220703,
            "C",
            NaN,
            NaN,
            false
        ],
        [
            2.7250075340270996,
            2.0179355144500732,
            9.323955535888672,
            "C",
            NaN,
            NaN,
            false
        ],
        [
            7.764403820037842,
            0.5176591873168945,
            19.026371002197266,
            "C",
            NaN,
            NaN,
            false
        ],
        [
            2.310696601867676,
            4.568350791931152,
            0.37582045793533325,
            "C",
            NaN,
            NaN,
            false
        ],
        [
            10.485153198242188,
            0.5196325778961182,
            0.37452051043510437,
            "C",
            NaN,
            NaN,
            false
        ],
        [
            -0.4100528657436371,
            4.566377639770508,
            19.02766990661621,
            "C",
            NaN,
            NaN,
            false
        ],
        [
            11.845941543579102,
            2.1335556507110596,
            8.962725639343262,
            "C",
            NaN,
            NaN,
            false
        ],
        [
            -1.7708410024642944,
            2.9524543285369873,
            10.439465522766113,
            "C",
            NaN,
            NaN,
            false
        ],
        [
            6.402464866638184,
            2.1326911449432373,
            10.440105438232422,
            "C",
            NaN,
            NaN,
            false
        ],
        [
            3.672635316848755,
            2.9533188343048096,
            8.962085723876953,
            "C",
            NaN,
            NaN,
            false
        ],
        [
            8.712733268737793,
            4.669338703155518,
            18.664152145385742,
            "C",
            NaN,
            NaN,
            false
        ],
        [
            1.3623672723770142,
            0.41667136549949646,
            0.7380399703979492,
            "C",
            NaN,
            NaN,
            false
        ],
        [
            9.5377197265625,
            4.67062520980835,
            0.7372056841850281,
            "C",
            NaN,
            NaN,
            false
        ],
        [
            0.5373806357383728,
            0.4153846204280853,
            18.66498565673828,
            "C",
            NaN,
            NaN,
            false
        ],
        [
            12.455456733703613,
            2.1697885990142822,
            7.686954021453857,
            "C",
            NaN,
            NaN,
            false
        ],
        [
            -2.3803563117980957,
            2.9162216186523438,
            11.71523666381836,
            "C",
            NaN,
            NaN,
            false
        ],
        [
            5.7934064865112305,
            2.1687510013580322,
            11.716032981872559,
            "C",
            NaN,
            NaN,
            false
        ],
        [
            4.281693935394287,
            2.9172589778900146,
            7.686158657073975,
            "C",
            NaN,
            NaN,
            false
        ],
        [
            9.323612213134766,
            4.707915782928467,
            17.389116287231445,
            "C",
            NaN,
            NaN,
            false
        ],
        [
            0.7514881491661072,
            0.37809908390045166,
            2.0130743980407715,
            "C",
            NaN,
            NaN,
            false
        ],
        [
            8.927160263061523,
            4.709009647369385,
            2.0124146938323975,
            "C",
            NaN,
            NaN,
            false
        ],
        [
            1.1479401588439941,
            0.37700048089027405,
            17.3897762298584,
            "C",
            NaN,
            NaN,
            false
        ],
        [
            13.479449272155762,
            1.2484831809997559,
            7.35007381439209,
            "C",
            NaN,
            NaN,
            false
        ],
        [
            -3.404348850250244,
            3.837526798248291,
            12.052117347717285,
            "C",
            NaN,
            NaN,
            false
        ],
        [
            4.770039081573486,
            1.2468912601470947,
            12.053203582763672,
            "C",
            NaN,
            NaN,
            false
        ],
        [
            5.305061340332031,
            3.839118719100952,
            7.348987579345703,
            "C",
            NaN,
            NaN,
            false
        ],
        [
            10.348370552062988,
            3.7876787185668945,
            17.05204200744629,
            "C",
            NaN,
            NaN,
            false
        ],
        [
            -0.2732701003551483,
            1.2983312606811523,
            2.3501486778259277,
            "C",
            NaN,
            NaN,
            false
        ],
        [
            7.902851104736328,
            3.788451910018921,
            2.349818706512451,
            "C",
            NaN,
            NaN,
            false
        ],
        [
            2.1722493171691895,
            1.2975581884384155,
            17.052371978759766,
            "C",
            NaN,
            NaN,
            false
        ],
        [
            14.300093650817871,
            3.128094434738159,
            1.8949731588363647,
            "H",
            NaN,
            NaN,
            false
        ],
        [
            -4.2249932289123535,
            1.9579155445098877,
            17.507217407226562,
            "H",
            NaN,
            NaN,
            false
        ],
        [
            3.9497885704040527,
            3.125922679901123,
            17.50840187072754,
            "H",
            NaN,
            NaN,
            false
        ],
        [
            6.125311851501465,
            1.9600871801376343,
            1.8937896490097046,
            "H",
            NaN,
            NaN,
            false
        ],
        [
            11.176304817199707,
            0.5899975299835205,
            11.601094245910645,
            "H",
            NaN,
            NaN,
            false
        ],
        [
            -1.1012042760849,
            4.4960126876831055,
            7.801097393035889,
            "H",
            NaN,
            NaN,
            false
        ],
        [
            7.075419902801514,
            0.5902518033981323,
            7.800981044769287,
            "H",
            NaN,
            NaN,
            false
        ],
        [
            2.999680280685425,
            4.495758056640625,
            11.601210594177246,
            "H",
            NaN,
            NaN,
            false
        ],
        [
            12.524373054504395,
            4.746172904968262,
            2.427097797393799,
            "H",
            NaN,
            NaN,
            false
        ],
        [
            -2.4492733478546143,
            0.3398370146751404,
            16.975093841552734,
            "H",
            NaN,
            NaN,
            false
        ],
        [
            5.725249290466309,
            4.74415397644043,
            16.976219177246094,
            "H",
            NaN,
            NaN,
            false
        ],
        [
            4.349841117858887,
            0.3418612480163574,
            2.425952911376953,
            "H",
            NaN,
            NaN,
            false
        ],
        [
            9.39976978302002,
            2.2068655490875244,
            12.13341236114502,
            "H",
            NaN,
            NaN,
            false
        ],
        [
            0.675330400466919,
            2.8791444301605225,
            7.2687788009643555,
            "H",
            NaN,
            NaN,
            false
        ],
        [
            8.851542472839355,
            2.207404613494873,
            7.268623352050781,
            "H",
            NaN,
            NaN,
            false
        ],
        [
            1.2235580682754517,
            2.878605365753174,
            12.133567810058594,
            "H",
            NaN,
            NaN,
            false
        ],
        [
            11.511945724487305,
            4.80145263671875,
            4.649095058441162,
            "H",
            NaN,
            NaN,
            false
        ],
        [
            -1.4368451833724976,
            0.28455716371536255,
            14.753096580505371,
            "H",
            NaN,
            NaN,
            false
        ],
        [
            6.736738681793213,
            4.80060338973999,
            14.753989219665527,
            "H",
            NaN,
            NaN,
            false
        ],
        [
            3.3383615016937256,
            0.28540652990341187,
            4.648202419281006,
            "H",
            NaN,
            NaN,
            false
        ],
        [
            8.383235931396484,
            2.2577764987945557,
            14.353798866271973,
            "H",
            NaN,
            NaN,
            false
        ],
        [
            1.6918646097183228,
            2.828233480453491,
            5.048391819000244,
            "H",
            NaN,
            NaN,
            false
        ],
        [
            9.866730690002441,
            2.2596633434295654,
            5.047596454620361,
            "H",
            NaN,
            NaN,
            false
        ],
        [
            0.20836997032165527,
            2.8263516426086426,
            14.354595184326172,
            "H",
            NaN,
            NaN,
            false
        ],
        [
            10.74444580078125,
            4.8662638664245605,
            6.447251319885254,
            "H",
            NaN,
            NaN,
            false
        ],
        [
            -0.6693457961082458,
            0.21974614262580872,
            12.954939842224121,
            "H",
            NaN,
            NaN,
            false
        ],
        [
            7.503520965576172,
            4.866040229797363,
            12.955269813537598,
            "H",
            NaN,
            NaN,
            false
        ],
        [
            2.5715792179107666,
            0.21996992826461792,
            6.446921348571777,
            "H",
            NaN,
            NaN,
            false
        ],
        [
            7.613884925842285,
            2.32016658782959,
            16.15191650390625,
            "H",
            NaN,
            NaN,
            false
        ],
        [
            2.4612152576446533,
            2.765843391418457,
            3.250274419784546,
            "H",
            NaN,
            NaN,
            false
        ],
        [
            10.635504722595215,
            2.3223636150360107,
            3.2489356994628906,
            "H",
            NaN,
            NaN,
            false
        ],
        [
            -0.5603980422019958,
            2.763646364212036,
            16.153236389160156,
            "H",
            NaN,
            NaN,
            false
        ],
        [
            9.777713775634766,
            4.812133312225342,
            8.672740936279297,
            "H",
            NaN,
            NaN,
            false
        ],
        [
            0.2973860800266266,
            0.2738765478134155,
            10.729450225830078,
            "H",
            NaN,
            NaN,
            false
        ],
        [
            8.469623565673828,
            4.812204837799072,
            10.729450225830078,
            "H",
            NaN,
            NaN,
            false
        ],
        [
            1.6054764986038208,
            0.273800253868103,
            8.672740936279297,
            "H",
            NaN,
            NaN,
            false
        ],
        [
            6.6456146240234375,
            2.2626030445098877,
            18.37680435180664,
            "H",
            NaN,
            NaN,
            false
        ],
        [
            3.42948579788208,
            2.823406934738159,
            1.0253864526748657,
            "H",
            NaN,
            NaN,
            false
        ],
        [
            11.603139877319336,
            2.2653698921203613,
            1.0234849452972412,
            "H",
            NaN,
            NaN,
            false
        ],
        [
            -1.5280392169952393,
            2.8206400871276855,
            18.378705978393555,
            "H",
            NaN,
            NaN,
            false
        ],
        [
            10.458303451538086,
            3.0479695796966553,
            10.319657325744629,
            "H",
            NaN,
            NaN,
            false
        ],
        [
            -0.3832034468650818,
            2.0380403995513916,
            9.082534790039062,
            "H",
            NaN,
            NaN,
            false
        ],
        [
            7.789210319519043,
            3.0477659702301025,
            9.082747459411621,
            "H",
            NaN,
            NaN,
            false
        ],
        [
            2.2858898639678955,
            2.0382440090179443,
            10.319443702697754,
            "H",
            NaN,
            NaN,
            false
        ],
        [
            13.59778118133545,
            0.4959978759288788,
            0.6189687252044678,
            "H",
            NaN,
            NaN,
            false
        ],
        [
            -3.5226805210113525,
            4.590012073516846,
            18.783222198486328,
            "H",
            NaN,
            NaN,
            false
        ],
        [
            4.651318073272705,
            0.4980678856372833,
            18.78166961669922,
            "H",
            NaN,
            NaN,
            false
        ],
        [
            5.4237823486328125,
            4.587942123413086,
            0.6205208897590637,
            "H",
            NaN,
            NaN,
            false
        ],
        [
            12.167156219482422,
            1.3658530712127686,
            9.665783882141113,
            "H",
            NaN,
            NaN,
            false
        ],
        [
            -2.0920722484588623,
            3.720151901245117,
            9.736407279968262,
            "H",
            NaN,
            NaN,
            false
        ],
        [
            6.081459045410156,
            1.3647748231887817,
            9.737260818481445,
            "H",
            NaN,
            NaN,
            false
        ],
        [
            3.9936413764953613,
            3.721240282058716,
            9.66493034362793,
            "H",
            NaN,
            NaN,
            false
        ],
        [
            9.033175468444824,
            3.900394916534424,
            19.366161346435547,
            "H",
            NaN,
            NaN,
            false
        ],
        [
            1.0419251918792725,
            1.185615062713623,
            0.0360298678278923,
            "H",
            NaN,
            NaN,
            false
        ],
        [
            9.21787166595459,
            3.901340961456299,
            0.03533139079809189,
            "H",
            NaN,
            NaN,
            false
        ],
        [
            0.8572289943695068,
            1.184669017791748,
            19.366859436035156,
            "H",
            NaN,
            NaN,
            false
        ],
        [
            -2.610412120819092,
            0.5163367986679077,
            8.110892295837402,
            "H",
            NaN,
            NaN,
            false
        ],
        [
            12.68551254272461,
            4.569668292999268,
            11.291298866271973,
            "H",
            NaN,
            NaN,
            false
        ],
        [
            4.51081657409668,
            0.5143482089042664,
            11.292579650878906,
            "H",
            NaN,
            NaN,
            false
        ],
        [
            5.56428337097168,
            4.571661949157715,
            8.109611511230469,
            "H",
            NaN,
            NaN,
            false
        ],
        [
            -5.742465019226074,
            3.0539710521698,
            17.811677932739258,
            "H",
            NaN,
            NaN,
            false
        ],
        [
            15.817564964294434,
            2.032038927078247,
            1.590514063835144,
            "H",
            NaN,
            NaN,
            false
        ],
        [
            7.643968105316162,
            3.0546271800994873,
            1.5903199911117554,
            "H",
            NaN,
            NaN,
            false
        ],
        [
            2.4311323165893555,
            2.0313827991485596,
            17.811870574951172,
            "H",
            NaN,
            NaN,
            false
        ]
    ],
    "dbname": "CSD",
    "dft": {
        "bandgap": 1.53477291,
        "Et": 1.56,
        "DF": -1.58522709,
        "VBdisp": 0.187,
        "CBdisp": 0.56,
        "hab": 0.06264,
        "gap_s": 1.9757916,
        "Et_s": 1.761265857,
        "DF_s": -1.546740114,
        "IP_s": 6.4522477,
        "EA_s": -1.1898499,
        "polarisation": 881.838,
        "apc": 176.0,
        "density": 0.873777254,
        "epsilon": 3.57088,
        "weight_s": 352.0
    }
}