{
    "properties": {
        "lattice_vector_a": [
            5.9967,
            0.0,
            0.0
        ],
        "lattice_vector_b": [
            -0.0782245730579176,
            7.465890208553158,
            0.0
        ],
        "lattice_vector_c": [
            -1.7645643255863874,
            -2.198013523324763,
            14.317379303914153
        ]
    },
    "struct_id": "PUJQIV",
    "input_ref": null,
    "geometry": [
        [
            1.3726911544799805,
            -0.27007776498794556,
            7.79824686050415,
            "C",
            NaN,
            NaN,
            false
        ],
        [
            2.096473455429077,
            -0.4897904098033905,
            7.01522970199585,
            "H",
            NaN,
            NaN,
            false
        ],
        [
            1.6873434782028198,
            -0.5726870894432068,
            9.100699424743652,
            "C",
            NaN,
            NaN,
            false
        ],
        [
            2.6502814292907715,
            -1.0228632688522339,
            9.336935997009277,
            "H",
            NaN,
            NaN,
            false
        ],
        [
            0.7669438719749451,
            -0.32413971424102783,
            10.153026580810547,
            "C",
            NaN,
            NaN,
            false
        ],
        [
            1.0466234683990479,
            -0.6586705446243286,
            11.502439498901367,
            "C",
            NaN,
            NaN,
            false
        ],
        [
            1.9965829849243164,
            -1.142776370048523,
            11.73452377319336,
            "H",
            NaN,
            NaN,
            false
        ],
        [
            0.12705229222774506,
            -0.38430437445640564,
            12.496495246887207,
            "C",
            NaN,
            NaN,
            false
        ],
        [
            0.34092679619789124,
            -0.6467772126197815,
            13.53264331817627,
            "H",
            NaN,
            NaN,
            false
        ],
        [
            -1.1057709455490112,
            0.23579886555671692,
            12.179508209228516,
            "C",
            NaN,
            NaN,
            false
        ],
        [
            4.1766462326049805,
            0.45450422167778015,
            12.972977638244629,
            "H",
            NaN,
            NaN,
            false
        ],
        [
            4.586945056915283,
            0.5628306865692139,
            10.875051498413086,
            "C",
            NaN,
            NaN,
            false
        ],
        [
            3.6364567279815674,
            1.0366437435150146,
            10.633660316467285,
            "H",
            NaN,
            NaN,
            false
        ],
        [
            -0.4909440577030182,
            0.288837194442749,
            9.827019691467285,
            "C",
            NaN,
            NaN,
            false
        ],
        [
            -0.784012496471405,
            0.5955820679664612,
            8.47574520111084,
            "C",
            NaN,
            NaN,
            false
        ],
        [
            4.247541904449463,
            1.0501043796539307,
            8.250103950500488,
            "H",
            NaN,
            NaN,
            false
        ],
        [
            0.11166925728321075,
            0.30380314588546753,
            7.450191497802734,
            "C",
            NaN,
            NaN,
            false
        ],
        [
            -0.23061229288578033,
            0.5197666883468628,
            6.043938636779785,
            "C",
            NaN,
            NaN,
            false
        ],
        [
            4.5651164054870605,
            1.093687891960144,
            5.545836925506592,
            "C",
            NaN,
            NaN,
            false
        ],
        [
            3.7419369220733643,
            1.486590027809143,
            6.1354265213012695,
            "H",
            NaN,
            NaN,
            false
        ],
        [
            4.606196880340576,
            1.0914885997772217,
            4.144022464752197,
            "C",
            NaN,
            NaN,
            false
        ],
        [
            3.6129443645477295,
            1.5868817567825317,
            3.297149181365967,
            "C",
            NaN,
            NaN,
            false
        ],
        [
            2.7302520275115967,
            1.9897139072418213,
            3.797255277633667,
            "H",
            NaN,
            NaN,
            false
        ],
        [
            3.602970600128174,
            1.6517608165740967,
            1.8994866609573364,
            "C",
            NaN,
            NaN,
            false
        ],
        [
            2.7209901809692383,
            2.123029947280884,
            1.4616612195968628,
            "H",
            NaN,
            NaN,
            false
        ],
        [
            4.568379878997803,
            1.1963467597961426,
            0.9924807548522949,
            "C",
            NaN,
            NaN,
            false
        ],
        [
            2.563837766647339,
            -0.8476529717445374,
            14.255098342895508,
            "H",
            NaN,
            NaN,
            false
        ],
        [
            5.796133995056152,
            0.5684157013893127,
            1.234014868736267,
            "C",
            NaN,
            NaN,
            false
        ],
        [
            0.3723291754722595,
            0.2897118628025055,
            0.3474828004837036,
            "H",
            NaN,
            NaN,
            false
        ],
        [
            0.3941422402858734,
            0.25212910771369934,
            2.459725856781006,
            "C",
            NaN,
            NaN,
            false
        ],
        [
            1.3679945468902588,
            -0.23538468778133392,
            2.401310920715332,
            "H",
            NaN,
            NaN,
            false
        ],
        [
            -0.08754641562700272,
            0.47662225365638733,
            3.7504374980926514,
            "C",
            NaN,
            NaN,
            false
        ],
        [
            0.5785176753997803,
            0.14421936869621277,
            4.938636779785156,
            "C",
            NaN,
            NaN,
            false
        ],
        [
            1.5564782619476318,
            -0.3272533118724823,
            4.9790120124816895,
            "H",
            NaN,
            NaN,
            false
        ],
        [
            2.178379535675049,
            3.5652716159820557,
            7.9525885581970215,
            "C",
            NaN,
            NaN,
            false
        ],
        [
            1.2039824724197388,
            3.1873555183410645,
            7.642760276794434,
            "H",
            NaN,
            NaN,
            false
        ],
        [
            2.508392572402954,
            3.5112388134002686,
            9.329204559326172,
            "C",
            NaN,
            NaN,
            false
        ],
        [
            1.602317214012146,
            3.002547264099121,
            10.295770645141602,
            "C",
            NaN,
            NaN,
            false
        ],
        [
            0.6519165635108948,
            2.5931246280670166,
            9.960171699523926,
            "H",
            NaN,
            NaN,
            false
        ],
        [
            1.9135873317718506,
            3.031013250350952,
            11.639313697814941,
            "C",
            NaN,
            NaN,
            false
        ],
        [
            1.209729790687561,
            2.6177725791931152,
            12.360050201416016,
            "H",
            NaN,
            NaN,
            false
        ],
        [
            3.1421241760253906,
            3.5807437896728516,
            12.077855110168457,
            "C",
            NaN,
            NaN,
            false
        ],
        [
            3.3648693561553955,
            3.6215133666992188,
            13.14478588104248,
            "H",
            NaN,
            NaN,
            false
        ],
        [
            4.059248924255371,
            4.060354709625244,
            11.162115097045898,
            "C",
            NaN,
            NaN,
            false
        ],
        [
            -0.9862648844718933,
            4.480213165283203,
            11.491987228393555,
            "H",
            NaN,
            NaN,
            false
        ],
        [
            3.771677255630493,
            4.030226707458496,
            9.773472785949707,
            "C",
            NaN,
            NaN,
            false
        ],
        [
            4.6723222732543945,
            4.530988693237305,
            8.796311378479004,
            "C",
            NaN,
            NaN,
            false
        ],
        [
            -0.35344669222831726,
            4.905609607696533,
            9.115446090698242,
            "H",
            NaN,
            NaN,
            false
        ],
        [
            4.3197550773620605,
            4.584354877471924,
            7.470235824584961,
            "C",
            NaN,
            NaN,
            false
        ],
        [
            5.024911880493164,
            5.0021185874938965,
            6.754080295562744,
            "H",
            NaN,
            NaN,
            false
        ],
        [
            3.0417137145996094,
            4.131160259246826,
            7.019524574279785,
            "C",
            NaN,
            NaN,
            false
        ],
        [
            2.656198024749756,
            4.3108296394348145,
            5.620143890380859,
            "C",
            NaN,
            NaN,
            false
        ],
        [
            3.453808307647705,
            4.9572649002075195,
            4.639976501464844,
            "C",
            NaN,
            NaN,
            false
        ],
        [
            4.435078144073486,
            5.399512767791748,
            4.788017749786377,
            "H",
            NaN,
            NaN,
            false
        ],
        [
            2.7782139778137207,
            4.936558723449707,
            3.4126906394958496,
            "C",
            NaN,
            NaN,
            false
        ],
        [
            3.2668490409851074,
            5.464837074279785,
            2.2169029712677,
            "C",
            NaN,
            NaN,
            false
        ],
        [
            4.238951683044434,
            5.955652236938477,
            2.2834787368774414,
            "H",
            NaN,
            NaN,
            false
        ],
        [
            2.6825788021087646,
            5.439201354980469,
            0.9478105306625366,
            "C",
            NaN,
            NaN,
            false
        ],
        [
            3.2555465698242188,
            5.9285078048706055,
            0.1590660810470581,
            "H",
            NaN,
            NaN,
            false
        ],
        [
            1.4579349756240845,
            4.882906436920166,
            0.5598095059394836,
            "C",
            NaN,
            NaN,
            false
        ],
        [
            -0.5417207479476929,
            2.772509813308716,
            13.813837051391602,
            "H",
            NaN,
            NaN,
            false
        ],
        [
            0.4825637638568878,
            4.242549896240234,
            1.333091139793396,
            "C",
            NaN,
            NaN,
            false
        ],
        [
            5.590576648712158,
            3.9091429710388184,
            0.7946145534515381,
            "H",
            NaN,
            NaN,
            false
        ],
        [
            0.4831974506378174,
            3.968858003616333,
            2.705411911010742,
            "C",
            NaN,
            NaN,
            false
        ],
        [
            -0.4027474522590637,
            3.459231376647949,
            3.087686061859131,
            "H",
            NaN,
            NaN,
            false
        ],
        [
            1.473191499710083,
            4.248014450073242,
            3.6497862339019775,
            "C",
            NaN,
            NaN,
            false
        ],
        [
            1.4418524503707886,
            3.8953092098236084,
            5.008648872375488,
            "C",
            NaN,
            NaN,
            false
        ],
        [
            0.6235215663909912,
            3.359349012374878,
            5.482697010040283,
            "H",
            NaN,
            NaN,
            false
        ]
    ],
    "dbname": "CSD",
    "dft": {
        "bandgap": 1.707,
        "Et": 1.757089865,
        "DF": -1.80717973,
        "VBdisp": 0.236,
        "CBdisp": 0.05,
        "hab": 0.06923,
        "gap_s": 1.9688393,
        "Et_s": 1.900607505,
        "DF_s": -1.83237571,
        "IP_s": 6.870055,
        "EA_s": -1.2059214,
        "polarisation": 656.759,
        "apc": 68.0,
        "density": 0.793546055,
        "epsilon": "N.C.",
        "weight_s": 254.0
    }
}