{
    "properties": {
        "lattice_vector_a": [
            13.1964,
            0.0,
            0.0
        ],
        "lattice_vector_b": [
            0.0,
            7.3412,
            0.0
        ],
        "lattice_vector_c": [
            -9.640676747884406,
            0.0,
            17.766342732616664
        ]
    },
    "struct_id": "PYRPYR10",
    "input_ref": null,
    "geometry": [
        [
            3.497802257537842,
            1.9859414100646973,
            5.449470520019531,
            "C",
            NaN,
            NaN,
            false
        ],
        [
            4.878259181976318,
            5.656541347503662,
            3.4337010383605957,
            "C",
            NaN,
            NaN,
            false
        ],
        [
            0.05792093649506569,
            5.355258464813232,
            12.316872596740723,
            "C",
            NaN,
            NaN,
            false
        ],
        [
            -1.3225361108779907,
            1.6846585273742676,
            14.3326416015625,
            "C",
            NaN,
            NaN,
            false
        ],
        [
            -0.22451941668987274,
            1.3879272937774658,
            5.208736419677734,
            "C",
            NaN,
            NaN,
            false
        ],
        [
            8.600581169128418,
            5.05852746963501,
            3.6744349002838135,
            "C",
            NaN,
            NaN,
            false
        ],
        [
            3.780242681503296,
            5.953272819519043,
            12.55760669708252,
            "C",
            NaN,
            NaN,
            false
        ],
        [
            -5.044857978820801,
            2.282672643661499,
            14.091907501220703,
            "C",
            NaN,
            NaN,
            false
        ],
        [
            -1.2853230237960815,
            1.5459098815917969,
            4.221282958984375,
            "C",
            NaN,
            NaN,
            false
        ],
        [
            9.661384582519531,
            5.216509819030762,
            4.661888122558594,
            "C",
            NaN,
            NaN,
            false
        ],
        [
            4.841046333312988,
            5.795289993286133,
            13.545060157775879,
            "C",
            NaN,
            NaN,
            false
        ],
        [
            -6.105661392211914,
            2.124690055847168,
            13.104454040527344,
            "C",
            NaN,
            NaN,
            false
        ],
        [
            -0.9340746402740479,
            1.6535319089889526,
            2.864112138748169,
            "C",
            NaN,
            NaN,
            false
        ],
        [
            9.310135841369629,
            5.324131965637207,
            6.019059181213379,
            "C",
            NaN,
            NaN,
            false
        ],
        [
            4.489798069000244,
            5.687668323516846,
            14.902230262756348,
            "C",
            NaN,
            NaN,
            false
        ],
        [
            -5.75441312789917,
            2.0170681476593018,
            11.747283935546875,
            "C",
            NaN,
            NaN,
            false
        ],
        [
            0.4168146252632141,
            2.068897008895874,
            2.510561943054199,
            "C",
            NaN,
            NaN,
            false
        ],
        [
            7.95924711227417,
            5.739497184753418,
            6.372609615325928,
            "C",
            NaN,
            NaN,
            false
        ],
        [
            3.138908624649048,
            5.272303104400635,
            15.255781173706055,
            "C",
            NaN,
            NaN,
            false
        ],
        [
            -4.403523921966553,
            1.6017030477523804,
            11.393733024597168,
            "C",
            NaN,
            NaN,
            false
        ],
        [
            0.7454265356063843,
            2.6071536540985107,
            1.2512835264205933,
            "C",
            NaN,
            NaN,
            false
        ],
        [
            7.6306352615356445,
            6.277753829956055,
            7.631887912750244,
            "C",
            NaN,
            NaN,
            false
        ],
        [
            2.8102967739105225,
            4.734046459197998,
            16.515058517456055,
            "C",
            NaN,
            NaN,
            false
        ],
        [
            -4.074911594390869,
            1.063446283340454,
            10.134454727172852,
            "C",
            NaN,
            NaN,
            false
        ],
        [
            2.03971004486084,
            3.0224454402923584,
            0.9393065571784973,
            "C",
            NaN,
            NaN,
            false
        ],
        [
            6.3363518714904785,
            6.693045616149902,
            7.943864822387695,
            "C",
            NaN,
            NaN,
            false
        ],
        [
            1.516013264656067,
            4.31875467300415,
            16.827035903930664,
            "C",
            NaN,
            NaN,
            false
        ],
        [
            -2.7806284427642822,
            0.6481545567512512,
            9.822478294372559,
            "C",
            NaN,
            NaN,
            false
        ],
        [
            3.057201385498047,
            2.917539596557617,
            1.8791460990905762,
            "C",
            NaN,
            NaN,
            false
        ],
        [
            5.318860054016113,
            6.588139533996582,
            7.004025459289551,
            "C",
            NaN,
            NaN,
            false
        ],
        [
            0.4985218048095703,
            4.4236602783203125,
            15.88719654083252,
            "C",
            NaN,
            NaN,
            false
        ],
        [
            -1.7631369829177856,
            0.7530602812767029,
            10.762317657470703,
            "C",
            NaN,
            NaN,
            false
        ],
        [
            10.499065399169922,
            1.5895166397094727,
            4.589223861694336,
            "C",
            NaN,
            NaN,
            false
        ],
        [
            -2.1230037212371826,
            5.2601165771484375,
            4.293947219848633,
            "C",
            NaN,
            NaN,
            false
        ],
        [
            -6.943342208862305,
            5.751683235168457,
            13.177118301391602,
            "C",
            NaN,
            NaN,
            false
        ],
        [
            5.678726673126221,
            2.081083297729492,
            13.472394943237305,
            "C",
            NaN,
            NaN,
            false
        ],
        [
            -3.1464388370513916,
            1.8981406688690186,
            5.88670015335083,
            "C",
            NaN,
            NaN,
            false
        ],
        [
            11.522500991821289,
            5.5687408447265625,
            2.996471405029297,
            "C",
            NaN,
            NaN,
            false
        ],
        [
            6.702162265777588,
            5.44305944442749,
            11.879642486572266,
            "C",
            NaN,
            NaN,
            false
        ],
        [
            -7.966777324676514,
            1.7724592685699463,
            14.769871711730957,
            "C",
            NaN,
            NaN,
            false
        ],
        [
            8.692471504211426,
            1.9606876373291016,
            6.196722507476807,
            "C",
            NaN,
            NaN,
            false
        ],
        [
            -0.316410094499588,
            5.631287574768066,
            2.686448574066162,
            "C",
            NaN,
            NaN,
            false
        ],
        [
            -5.136748313903809,
            5.380512237548828,
            11.569620132446289,
            "C",
            NaN,
            NaN,
            false
        ],
        [
            3.872133255004883,
            1.7099123001098633,
            15.079894065856934,
            "C",
            NaN,
            NaN,
            false
        ],
        [
            3.779775619506836,
            2.4311118125915527,
            4.193212032318115,
            "C",
            NaN,
            NaN,
            false
        ],
        [
            4.596285820007324,
            6.101711750030518,
            4.6899590492248535,
            "C",
            NaN,
            NaN,
            false
        ],
        [
            -0.22405235469341278,
            4.910088062286377,
            13.57313060760498,
            "C",
            NaN,
            NaN,
            false
        ],
        [
            -1.0405627489089966,
            1.2394882440567017,
            13.076383590698242,
            "C",
            NaN,
            NaN,
            false
        ],
        [
            7.727198600769043,
            1.714537262916565,
            5.233609199523926,
            "C",
            NaN,
            NaN,
            false
        ],
        [
            0.648862898349762,
            5.38513708114624,
            3.649562120437622,
            "C",
            NaN,
            NaN,
            false
        ],
        [
            -4.171475410461426,
            5.626662731170654,
            12.532733917236328,
            "C",
            NaN,
            NaN,
            false
        ],
        [
            2.9068603515625,
            1.9560627937316895,
            14.116780281066895,
            "C",
            NaN,
            NaN,
            false
        ],
        [
            8.115371704101562,
            1.4454822540283203,
            3.9112603664398193,
            "C",
            NaN,
            NaN,
            false
        ],
        [
            0.26068949699401855,
            5.116082191467285,
            4.9719109535217285,
            "C",
            NaN,
            NaN,
            false
        ],
        [
            -4.5596489906311035,
            5.895717620849609,
            13.855082511901855,
            "C",
            NaN,
            NaN,
            false
        ],
        [
            3.2950336933135986,
            2.2251176834106445,
            12.794431686401367,
            "C",
            NaN,
            NaN,
            false
        ],
        [
            9.505204200744629,
            1.4195678234100342,
            3.5768978595733643,
            "C",
            NaN,
            NaN,
            false
        ],
        [
            -1.1291424036026,
            5.090167999267578,
            5.306273460388184,
            "C",
            NaN,
            NaN,
            false
        ],
        [
            -5.9494805335998535,
            5.921632289886475,
            14.189444541931152,
            "C",
            NaN,
            NaN,
            false
        ],
        [
            4.684865474700928,
            2.2510321140289307,
            12.460068702697754,
            "C",
            NaN,
            NaN,
            false
        ],
        [
            9.89677906036377,
            1.192651391029358,
            2.2273664474487305,
            "C",
            NaN,
            NaN,
            false
        ],
        [
            -1.5207171440124512,
            4.863251209259033,
            6.6558051109313965,
            "C",
            NaN,
            NaN,
            false
        ],
        [
            -6.341055393218994,
            6.148548603057861,
            15.538976669311523,
            "C",
            NaN,
            NaN,
            false
        ],
        [
            5.076440334320068,
            2.4779486656188965,
            11.1105375289917,
            "C",
            NaN,
            NaN,
            false
        ],
        [
            11.270520210266113,
            1.3005670309066772,
            1.8548061847686768,
            "C",
            NaN,
            NaN,
            false
        ],
        [
            -2.894458532333374,
            4.971167087554932,
            7.028365135192871,
            "C",
            NaN,
            NaN,
            false
        ],
        [
            -7.714797019958496,
            6.040633201599121,
            15.91153621673584,
            "C",
            NaN,
            NaN,
            false
        ],
        [
            6.45018196105957,
            2.370033025741577,
            10.737977981567383,
            "C",
            NaN,
            NaN,
            false
        ],
        [
            11.621331214904785,
            0.889900267124176,
            0.5541322231292725,
            "C",
            NaN,
            NaN,
            false
        ],
        [
            -3.245269298553467,
            4.560500144958496,
            8.329039573669434,
            "C",
            NaN,
            NaN,
            false
        ],
        [
            -8.065608024597168,
            6.451299667358398,
            17.212209701538086,
            "C",
            NaN,
            NaN,
            false
        ],
        [
            6.800992488861084,
            2.7806997299194336,
            9.43730354309082,
            "C",
            NaN,
            NaN,
            false
        ],
        [
            1.0276495218276978,
            0.46785467863082886,
            17.393604278564453,
            "C",
            NaN,
            NaN,
            false
        ],
        [
            -2.292264699935913,
            4.138454914093018,
            9.255908966064453,
            "C",
            NaN,
            NaN,
            false
        ],
        [
            2.528073787689209,
            6.873345375061035,
            0.3727378845214844,
            "C",
            NaN,
            NaN,
            false
        ],
        [
            5.847987651824951,
            3.2027454376220703,
            8.510433197021484,
            "C",
            NaN,
            NaN,
            false
        ],
        [
            -0.32155874371528625,
            0.47659069299697876,
            17.721927642822266,
            "C",
            NaN,
            NaN,
            false
        ],
        [
            -0.9430563449859619,
            4.147190570831299,
            8.927587509155273,
            "C",
            NaN,
            NaN,
            false
        ],
        [
            3.877281904220581,
            6.864609241485596,
            0.04441585764288902,
            "C",
            NaN,
            NaN,
            false
        ],
        [
            4.498779773712158,
            3.194009304046631,
            8.83875560760498,
            "C",
            NaN,
            NaN,
            false
        ],
        [
            8.91067886352539,
            0.8450455069541931,
            1.2498621940612793,
            "C",
            NaN,
            NaN,
            false
        ],
        [
            -0.5346168875694275,
            4.515645503997803,
            7.633309364318848,
            "C",
            NaN,
            NaN,
            false
        ],
        [
            -5.354955196380615,
            6.496154308319092,
            16.516481399536133,
            "C",
            NaN,
            NaN,
            false
        ],
        [
            4.0903401374816895,
            2.825554370880127,
            10.133033752441406,
            "C",
            NaN,
            NaN,
            false
        ],
        [
            7.530359268188477,
            0.8637655973434448,
            1.6238436698913574,
            "C",
            NaN,
            NaN,
            false
        ],
        [
            0.8457021713256836,
            4.534365653991699,
            7.259327411651611,
            "C",
            NaN,
            NaN,
            false
        ],
        [
            -3.9746363162994385,
            6.4774346351623535,
            16.142499923706055,
            "C",
            NaN,
            NaN,
            false
        ],
        [
            2.7100210189819336,
            2.8068344593048096,
            10.507015228271484,
            "C",
            NaN,
            NaN,
            false
        ],
        [
            2.7691447734832764,
            2.4699466228485107,
            3.180175304412842,
            "C",
            NaN,
            NaN,
            false
        ],
        [
            5.606916904449463,
            6.140546798706055,
            5.702996253967285,
            "C",
            NaN,
            NaN,
            false
        ],
        [
            0.7865785956382751,
            4.871253490447998,
            14.586167335510254,
            "C",
            NaN,
            NaN,
            false
        ],
        [
            -2.0511937141418457,
            1.200653314590454,
            12.063346862792969,
            "C",
            NaN,
            NaN,
            false
        ],
        [
            7.148217678070068,
            1.1742984056472778,
            2.8932487964630127,
            "C",
            NaN,
            NaN,
            false
        ],
        [
            1.2278441190719604,
            4.844898223876953,
            5.989922523498535,
            "C",
            NaN,
            NaN,
            false
        ],
        [
            -3.592494249343872,
            6.166901588439941,
            14.873093605041504,
            "C",
            NaN,
            NaN,
            false
        ],
        [
            2.3278791904449463,
            2.4963016510009766,
            11.776420593261719,
            "C",
            NaN,
            NaN,
            false
        ],
        [
            1.4363458156585693,
            2.0644922256469727,
            3.509385585784912,
            "C",
            NaN,
            NaN,
            false
        ],
        [
            6.93971586227417,
            5.7350921630859375,
            5.373785495758057,
            "C",
            NaN,
            NaN,
            false
        ],
        [
            2.119377374649048,
            5.276707649230957,
            14.256957054138184,
            "C",
            NaN,
            NaN,
            false
        ],
        [
            -3.3839926719665527,
            1.6061077117919922,
            12.392557144165039,
            "C",
            NaN,
            NaN,
            false
        ],
        [
            1.127103328704834,
            1.663589358329773,
            4.839729309082031,
            "C",
            NaN,
            NaN,
            false
        ],
        [
            7.248958110809326,
            5.334189414978027,
            4.0434417724609375,
            "C",
            NaN,
            NaN,
            false
        ],
        [
            2.428619861602783,
            5.677610874176025,
            12.926612854003906,
            "C",
            NaN,
            NaN,
            false
        ],
        [
            -3.693234920501709,
            2.0070106983184814,
            13.722900390625,
            "C",
            NaN,
            NaN,
            false
        ],
        [
            2.1730077266693115,
            1.5799731016159058,
            5.812081336975098,
            "C",
            NaN,
            NaN,
            false
        ],
        [
            6.203053951263428,
            5.25057315826416,
            3.07108998298645,
            "C",
            NaN,
            NaN,
            false
        ],
        [
            1.3827154636383057,
            5.761227130889893,
            11.954261779785156,
            "C",
            NaN,
            NaN,
            false
        ],
        [
            -2.6473305225372314,
            2.0906269550323486,
            14.695252418518066,
            "C",
            NaN,
            NaN,
            false
        ],
        [
            1.8725614547729492,
            1.1435387134552002,
            7.1118669509887695,
            "C",
            NaN,
            NaN,
            false
        ],
        [
            6.503499984741211,
            4.814138889312744,
            1.7713043689727783,
            "C",
            NaN,
            NaN,
            false
        ],
        [
            1.683161735534668,
            6.197661399841309,
            10.654476165771484,
            "C",
            NaN,
            NaN,
            false
        ],
        [
            -2.9477767944335938,
            2.5270612239837646,
            15.995038032531738,
            "C",
            NaN,
            NaN,
            false
        ],
        [
            0.5792942047119141,
            0.7518122792243958,
            7.430239677429199,
            "C",
            NaN,
            NaN,
            false
        ],
        [
            7.796767234802246,
            4.422412395477295,
            1.452931523323059,
            "C",
            NaN,
            NaN,
            false
        ],
        [
            2.976428985595703,
            6.589387893676758,
            10.336102485656738,
            "C",
            NaN,
            NaN,
            false
        ],
        [
            -4.241044044494629,
            2.918787717819214,
            16.313411712646484,
            "C",
            NaN,
            NaN,
            false
        ],
        [
            -0.44770270586013794,
            0.8644996881484985,
            6.496973991394043,
            "C",
            NaN,
            NaN,
            false
        ],
        [
            8.82376480102539,
            4.535099506378174,
            2.386197566986084,
            "C",
            NaN,
            NaN,
            false
        ],
        [
            4.0034260749816895,
            6.476700305938721,
            11.269369125366211,
            "C",
            NaN,
            NaN,
            false
        ],
        [
            -5.268041133880615,
            2.806100368499756,
            15.380145072937012,
            "C",
            NaN,
            NaN,
            false
        ],
        [
            4.278775215148926,
            1.9397653341293335,
            6.20844841003418,
            "H",
            NaN,
            NaN,
            false
        ],
        [
            4.097286224365234,
            5.610365390777588,
            2.674722909927368,
            "H",
            NaN,
            NaN,
            false
        ],
        [
            -0.7230519652366638,
            5.401434898376465,
            11.557894706726074,
            "H",
            NaN,
            NaN,
            false
        ],
        [
            -0.5415631532669067,
            1.730834722518921,
            15.091619491577148,
            "H",
            NaN,
            NaN,
            false
        ],
        [
            -0.033559150993824005,
            2.740323066711426,
            0.5088280439376831,
            "H",
            NaN,
            NaN,
            false
        ],
        [
            8.409621238708496,
            6.410923004150391,
            8.374342918395996,
            "H",
            NaN,
            NaN,
            false
        ],
        [
            3.589282512664795,
            4.600876808166504,
            17.25751495361328,
            "H",
            NaN,
            NaN,
            false
        ],
        [
            -4.853897571563721,
            0.9302768707275391,
            9.391999244689941,
            "H",
            NaN,
            NaN,
            false
        ],
        [
            -7.395910739898682,
            3.4351677894592285,
            17.71784019470215,
            "H",
            NaN,
            NaN,
            false
        ],
        [
            6.131295680999756,
            7.105767726898193,
            8.931673049926758,
            "H",
            NaN,
            NaN,
            false
        ],
        [
            10.951634407043457,
            3.9060323238372803,
            0.048502117395401,
            "H",
            NaN,
            NaN,
            false
        ],
        [
            -2.5755724906921387,
            0.23543228209018707,
            8.83466911315918,
            "H",
            NaN,
            NaN,
            false
        ],
        [
            4.081039905548096,
            3.1970925331115723,
            1.632193922996521,
            "H",
            NaN,
            NaN,
            false
        ],
        [
            4.2950215339660645,
            6.867692470550537,
            7.250977516174316,
            "H",
            NaN,
            NaN,
            false
        ],
        [
            -0.5253168344497681,
            4.144107341766357,
            16.1341495513916,
            "H",
            NaN,
            NaN,
            false
        ],
        [
            -0.7392982840538025,
            0.4735074043273926,
            10.515365600585938,
            "H",
            NaN,
            NaN,
            false
        ],
        [
            -2.434921979904175,
            2.1561105251312256,
            6.663266658782959,
            "H",
            NaN,
            NaN,
            false
        ],
        [
            10.810983657836914,
            5.826710224151611,
            2.2199044227600098,
            "H",
            NaN,
            NaN,
            false
        ],
        [
            5.990645408630371,
            5.185089588165283,
            11.103075981140137,
            "H",
            NaN,
            NaN,
            false
        ],
        [
            -7.255260467529297,
            1.5144895315170288,
            15.546438217163086,
            "H",
            NaN,
            NaN,
            false
        ],
        [
            8.39693832397461,
            2.207719087600708,
            7.213135242462158,
            "H",
            NaN,
            NaN,
            false
        ],
        [
            -0.020877137780189514,
            5.878319263458252,
            1.6700361967086792,
            "H",
            NaN,
            NaN,
            false
        ],
        [
            -4.84121561050415,
            5.133481025695801,
            10.553207397460938,
            "H",
            NaN,
            NaN,
            false
        ],
        [
            3.5766003131866455,
            1.4628809690475464,
            16.09630584716797,
            "H",
            NaN,
            NaN,
            false
        ],
        [
            4.780889511108398,
            2.7773962020874023,
            3.9375545978546143,
            "H",
            NaN,
            NaN,
            false
        ],
        [
            3.5951719284057617,
            6.447996139526367,
            4.945616722106934,
            "H",
            NaN,
            NaN,
            false
        ],
        [
            -1.2251664400100708,
            4.563803672790527,
            13.828787803649902,
            "H",
            NaN,
            NaN,
            false
        ],
        [
            -0.039448682218790054,
            0.8932037949562073,
            12.820725440979004,
            "H",
            NaN,
            NaN,
            false
        ],
        [
            6.669031143188477,
            1.7190887928009033,
            5.492997646331787,
            "H",
            NaN,
            NaN,
            false
        ],
        [
            1.7070305347442627,
            5.389688968658447,
            3.3901734352111816,
            "H",
            NaN,
            NaN,
            false
        ],
        [
            -3.1133079528808594,
            5.6221113204956055,
            12.273344993591309,
            "H",
            NaN,
            NaN,
            false
        ],
        [
            1.848692774772644,
            1.9515111446380615,
            14.376169204711914,
            "H",
            NaN,
            NaN,
            false
        ],
        [
            12.6697416305542,
            0.8396130204200745,
            0.2815965414047241,
            "H",
            NaN,
            NaN,
            false
        ],
        [
            -4.293679714202881,
            4.5102128982543945,
            8.601574897766113,
            "H",
            NaN,
            NaN,
            false
        ],
        [
            -9.114018440246582,
            6.5015869140625,
            17.4847469329834,
            "H",
            NaN,
            NaN,
            false
        ],
        [
            7.849402904510498,
            2.830986976623535,
            9.16476821899414,
            "H",
            NaN,
            NaN,
            false
        ],
        [
            1.3506163358688354,
            0.11892744153738022,
            16.4127254486084,
            "H",
            NaN,
            NaN,
            false
        ],
        [
            -2.615231513977051,
            3.789527416229248,
            10.236788749694824,
            "H",
            NaN,
            NaN,
            false
        ],
        [
            2.2051069736480713,
            7.2222723960876465,
            1.3536176681518555,
            "H",
            NaN,
            NaN,
            false
        ],
        [
            6.170954704284668,
            3.5516724586486816,
            7.5295538902282715,
            "H",
            NaN,
            NaN,
            false
        ],
        [
            -1.0681707859039307,
            0.16436946392059326,
            16.991552352905273,
            "H",
            NaN,
            NaN,
            false
        ],
        [
            -0.19644439220428467,
            3.8349695205688477,
            9.65796184539795,
            "H",
            NaN,
            NaN,
            false
        ],
        [
            4.623894214630127,
            7.176830768585205,
            0.7747902274131775,
            "H",
            NaN,
            NaN,
            false
        ],
        [
            3.7521677017211914,
            3.506230592727661,
            8.108381271362305,
            "H",
            NaN,
            NaN,
            false
        ],
        [
            6.78475284576416,
            0.6296547055244446,
            0.8648655414581299,
            "H",
            NaN,
            NaN,
            false
        ],
        [
            1.5913087129592896,
            4.300254821777344,
            8.018305778503418,
            "H",
            NaN,
            NaN,
            false
        ],
        [
            -3.229029655456543,
            6.711545467376709,
            16.901477813720703,
            "H",
            NaN,
            NaN,
            false
        ],
        [
            1.9644145965576172,
            3.040945291519165,
            9.748037338256836,
            "H",
            NaN,
            NaN,
            false
        ],
        [
            6.0937066078186035,
            1.1750324964523315,
            3.168272018432617,
            "H",
            NaN,
            NaN,
            false
        ],
        [
            2.2823548316955566,
            4.845632553100586,
            5.71489953994751,
            "H",
            NaN,
            NaN,
            false
        ],
        [
            -2.5379834175109863,
            6.166167736053467,
            14.598071098327637,
            "H",
            NaN,
            NaN,
            false
        ],
        [
            1.2733683586120605,
            2.495567560195923,
            12.051443099975586,
            "H",
            NaN,
            NaN,
            false
        ],
        [
            2.664323091506958,
            1.1138068437576294,
            7.8594746589660645,
            "H",
            NaN,
            NaN,
            false
        ],
        [
            5.711738586425781,
            4.784406661987305,
            1.0236966609954834,
            "H",
            NaN,
            NaN,
            false
        ],
        [
            0.8914000988006592,
            6.22739315032959,
            9.906867980957031,
            "H",
            NaN,
            NaN,
            false
        ],
        [
            -2.156015157699585,
            2.556793212890625,
            16.742645263671875,
            "H",
            NaN,
            NaN,
            false
        ],
        [
            0.3563165068626404,
            0.3520839512348175,
            8.417515754699707,
            "H",
            NaN,
            NaN,
            false
        ],
        [
            8.019744873046875,
            4.022684097290039,
            0.4656558334827423,
            "H",
            NaN,
            NaN,
            false
        ],
        [
            3.199406862258911,
            6.989116191864014,
            9.348827362060547,
            "H",
            NaN,
            NaN,
            false
        ],
        [
            -4.464021682739258,
            3.3185160160064697,
            17.300687789916992,
            "H",
            NaN,
            NaN,
            false
        ],
        [
            -1.4310760498046875,
            0.4931083917617798,
            6.763469219207764,
            "H",
            NaN,
            NaN,
            false
        ],
        [
            9.807137489318848,
            4.163708209991455,
            2.1197023391723633,
            "H",
            NaN,
            NaN,
            false
        ],
        [
            4.986799240112305,
            6.8480916023254395,
            11.002873420715332,
            "H",
            NaN,
            NaN,
            false
        ],
        [
            -6.2514142990112305,
            3.1774916648864746,
            15.64664077758789,
            "H",
            NaN,
            NaN,
            false
        ]
    ],
    "dbname": "CSD",
    "dft": {
        "bandgap": 1.80212502,
        "Et": 1.8519,
        "DF": -1.90167498,
        "VBdisp": 0.158,
        "CBdisp": 0.08,
        "hab": 0.05945,
        "gap_s": 2.1542285,
        "Et_s": 1.920003854,
        "DF_s": -1.685779208,
        "IP_s": 6.4770109,
        "EA_s": -1.0917278,
        "polarisation": 940.484,
        "apc": 184.0,
        "density": 0.874892805,
        "epsilon": 3.52116,
        "weight_s": 376.0
    }
}